<?xml version="1.0" ?>
<annotation>
    <folder>AIA AUTO</folder>
    <filename>000029_flip_type-1.jpg</filename>
    <source>
        <database>The AUTO Database</database>
        <annotation>AUTO by zxl</annotation>
        <image>flickr</image>
    </source>
    <size>
        <width>512</width>
        <height>512</height>
        <depth>3</depth>
    </size>
    <object>
        <name>eddy</name>
        <pose>front</pose>
        <truncated>0</truncated>
        <difficult>0</difficult>
        <bndbox>
            <xmin>213</xmin>
            <ymin>273</ymin>
            <xmax>379</xmax>
            <ymax>371</ymax>
        </bndbox>
    </object>
    <object>
        <name>eddy</name>
        <pose>front</pose>
        <truncated>0</truncated>
        <difficult>0</difficult>
        <bndbox>
            <xmin>24</xmin>
            <ymin>330</ymin>
            <xmax>119</xmax>
            <ymax>388</ymax>
        </bndbox>
    </object>
    <object>
        <name>eddy</name>
        <pose>front</pose>
        <truncated>0</truncated>
        <difficult>0</difficult>
        <bndbox>
            <xmin>208</xmin>
            <ymin>110</ymin>
            <xmax>257</xmax>
            <ymax>144</ymax>
        </bndbox>
    </object>
</annotation>
