<annotation>
	<folder>JPEGImages</folder>
	<filename>000162.jpg</filename>
	<path>E:\PycharmProjects\R-CNN\simple-faster-rcnn\Eddy-RCNN-pytorch-master\VOCdevkit\VOC2007\2500\JPEGImages\000162.jpg</path>
	<source>
		<database>Unknown</database>
	</source>
	<size>
		<width>512</width>
		<height>512</height>
		<depth>3</depth>
	</size>
	<segmented>0</segmented>
	<object>
		<name>eddy</name>
		<pose>Unspecified</pose>
		<truncated>0</truncated>
		<difficult>0</difficult>
		<bndbox>
			<xmin>434</xmin>
			<ymin>166</ymin>
			<xmax>508</xmax>
			<ymax>220</ymax>
		</bndbox>
	</object>
	<object>
		<name>eddy</name>
		<pose>Unspecified</pose>
		<truncated>0</truncated>
		<difficult>0</difficult>
		<bndbox>
			<xmin>414</xmin>
			<ymin>101</ymin>
			<xmax>496</xmax>
			<ymax>149</ymax>
		</bndbox>
	</object>
	<object>
		<name>eddy</name>
		<pose>Unspecified</pose>
		<truncated>0</truncated>
		<difficult>0</difficult>
		<bndbox>
			<xmin>40</xmin>
			<ymin>128</ymin>
			<xmax>164</xmax>
			<ymax>202</ymax>
		</bndbox>
	</object>
	<object>
		<name>eddy</name>
		<pose>Unspecified</pose>
		<truncated>0</truncated>
		<difficult>0</difficult>
		<bndbox>
			<xmin>337</xmin>
			<ymin>16</ymin>
			<xmax>390</xmax>
			<ymax>54</ymax>
		</bndbox>
	</object>
	<object>
		<name>eddy</name>
		<pose>Unspecified</pose>
		<truncated>0</truncated>
		<difficult>0</difficult>
		<bndbox>
			<xmin>160</xmin>
			<ymin>247</ymin>
			<xmax>222</xmax>
			<ymax>304</ymax>
		</bndbox>
	</object>
</annotation>
