<annotation>
	<folder>512crop_jpg</folder>
	<filename>002776_rsize1024x600_crop512_0_wh512x512.jpg</filename>
	<path>F:\VOCData\augment\2500\512crop_jpg\002776_rsize1024x600_crop512_0_wh512x512.jpg</path>
	<source>
		<database>Unknown</database>
	</source>
	<size>
		<width>512</width>
		<height>512</height>
		<depth>3</depth>
	</size>
	<segmented>0</segmented>
	<object>
		<name>eddy</name>
		<pose>Unspecified</pose>
		<truncated>0</truncated>
		<difficult>0</difficult>
		<bndbox>
			<xmin>347</xmin>
			<ymin>40</ymin>
			<xmax>459</xmax>
			<ymax>106</ymax>
		</bndbox>
	</object>
	<object>
		<name>eddy</name>
		<pose>Unspecified</pose>
		<truncated>0</truncated>
		<difficult>0</difficult>
		<bndbox>
			<xmin>214</xmin>
			<ymin>218</ymin>
			<xmax>307</xmax>
			<ymax>292</ymax>
		</bndbox>
	</object>
	<object>
		<name>eddy</name>
		<pose>Unspecified</pose>
		<truncated>1</truncated>
		<difficult>0</difficult>
		<bndbox>
			<xmin>5</xmin>
			<ymin>465</ymin>
			<xmax>86</xmax>
			<ymax>512</ymax>
		</bndbox>
	</object>
	<object>
		<name>eddy</name>
		<pose>Unspecified</pose>
		<truncated>0</truncated>
		<difficult>0</difficult>
		<bndbox>
			<xmin>4</xmin>
			<ymin>396</ymin>
			<xmax>51</xmax>
			<ymax>428</ymax>
		</bndbox>
	</object>
</annotation>
