<?xml version="1.0" ?>
<annotation>
    <folder>AIA AUTO</folder>
    <filename>001642_flip_type1.jpg</filename>
    <source>
        <database>The AUTO Database</database>
        <annotation>AUTO by zxl</annotation>
        <image>flickr</image>
    </source>
    <size>
        <width>512</width>
        <height>512</height>
        <depth>3</depth>
    </size>
    <object>
        <name>eddy</name>
        <pose>front</pose>
        <truncated>0</truncated>
        <difficult>0</difficult>
        <bndbox>
            <xmin>1</xmin>
            <ymin>19</ymin>
            <xmax>73</xmax>
            <ymax>66</ymax>
        </bndbox>
    </object>
    <object>
        <name>eddy</name>
        <pose>front</pose>
        <truncated>0</truncated>
        <difficult>0</difficult>
        <bndbox>
            <xmin>191</xmin>
            <ymin>31</ymin>
            <xmax>313</xmax>
            <ymax>104</ymax>
        </bndbox>
    </object>
    <object>
        <name>eddy</name>
        <pose>front</pose>
        <truncated>0</truncated>
        <difficult>0</difficult>
        <bndbox>
            <xmin>4</xmin>
            <ymin>184</ymin>
            <xmax>101</xmax>
            <ymax>256</ymax>
        </bndbox>
    </object>
    <object>
        <name>eddy</name>
        <pose>front</pose>
        <truncated>0</truncated>
        <difficult>0</difficult>
        <bndbox>
            <xmin>234</xmin>
            <ymin>201</ymin>
            <xmax>311</xmax>
            <ymax>261</ymax>
        </bndbox>
    </object>
    <object>
        <name>eddy</name>
        <pose>front</pose>
        <truncated>0</truncated>
        <difficult>0</difficult>
        <bndbox>
            <xmin>396</xmin>
            <ymin>149</ymin>
            <xmax>445</xmax>
            <ymax>202</ymax>
        </bndbox>
    </object>
    <object>
        <name>eddy</name>
        <pose>front</pose>
        <truncated>0</truncated>
        <difficult>0</difficult>
        <bndbox>
            <xmin>0</xmin>
            <ymin>303</ymin>
            <xmax>41</xmax>
            <ymax>372</ymax>
        </bndbox>
    </object>
    <object>
        <name>eddy</name>
        <pose>front</pose>
        <truncated>0</truncated>
        <difficult>0</difficult>
        <bndbox>
            <xmin>54</xmin>
            <ymin>293</ymin>
            <xmax>106</xmax>
            <ymax>356</ymax>
        </bndbox>
    </object>
    <object>
        <name>eddy</name>
        <pose>front</pose>
        <truncated>0</truncated>
        <difficult>0</difficult>
        <bndbox>
            <xmin>388</xmin>
            <ymin>279</ymin>
            <xmax>470</xmax>
            <ymax>353</ymax>
        </bndbox>
    </object>
    <object>
        <name>eddy</name>
        <pose>front</pose>
        <truncated>0</truncated>
        <difficult>0</difficult>
        <bndbox>
            <xmin>186</xmin>
            <ymin>358</ymin>
            <xmax>271</xmax>
            <ymax>435</ymax>
        </bndbox>
    </object>
    <object>
        <name>eddy</name>
        <pose>front</pose>
        <truncated>0</truncated>
        <difficult>0</difficult>
        <bndbox>
            <xmin>288</xmin>
            <ymin>330</ymin>
            <xmax>339</xmax>
            <ymax>379</ymax>
        </bndbox>
    </object>
    <object>
        <name>eddy</name>
        <pose>front</pose>
        <truncated>0</truncated>
        <difficult>0</difficult>
        <bndbox>
            <xmin>14</xmin>
            <ymin>389</ymin>
            <xmax>66</xmax>
            <ymax>426</ymax>
        </bndbox>
    </object>
    <object>
        <name>eddy</name>
        <pose>front</pose>
        <truncated>0</truncated>
        <difficult>0</difficult>
        <bndbox>
            <xmin>414</xmin>
            <ymin>362</ymin>
            <xmax>456</xmax>
            <ymax>407</ymax>
        </bndbox>
    </object>
    <object>
        <name>eddy</name>
        <pose>front</pose>
        <truncated>0</truncated>
        <difficult>0</difficult>
        <bndbox>
            <xmin>144</xmin>
            <ymin>245</ymin>
            <xmax>177</xmax>
            <ymax>298</ymax>
        </bndbox>
    </object>
    <object>
        <name>eddy</name>
        <pose>front</pose>
        <truncated>0</truncated>
        <difficult>0</difficult>
        <bndbox>
            <xmin>405</xmin>
            <ymin>423</ymin>
            <xmax>439</xmax>
            <ymax>479</ymax>
        </bndbox>
    </object>
</annotation>
