<annotation>
	<folder>img</folder>
	<filename>001585.jpg</filename>
	<path>F:\VOCData\augment\291\img\001585.jpg</path>
	<source>
		<database>Unknown</database>
	</source>
	<size>
		<width>512</width>
		<height>512</height>
		<depth>3</depth>
	</size>
	<segmented>0</segmented>
	<object>
		<name>eddy</name>
		<pose>Unspecified</pose>
		<truncated>0</truncated>
		<difficult>0</difficult>
		<bndbox>
			<xmin>171</xmin>
			<ymin>358</ymin>
			<xmax>223</xmax>
			<ymax>403</ymax>
		</bndbox>
	</object>
	<object>
		<name>eddy</name>
		<pose>Unspecified</pose>
		<truncated>0</truncated>
		<difficult>0</difficult>
		<bndbox>
			<xmin>251</xmin>
			<ymin>148</ymin>
			<xmax>295</xmax>
			<ymax>189</ymax>
		</bndbox>
	</object>
	<object>
		<name>eddy</name>
		<pose>Unspecified</pose>
		<truncated>0</truncated>
		<difficult>0</difficult>
		<bndbox>
			<xmin>375</xmin>
			<ymin>425</ymin>
			<xmax>410</xmax>
			<ymax>472</ymax>
		</bndbox>
	</object>
	<object>
		<name>eddy</name>
		<pose>Unspecified</pose>
		<truncated>0</truncated>
		<difficult>0</difficult>
		<bndbox>
			<xmin>295</xmin>
			<ymin>464</ymin>
			<xmax>329</xmax>
			<ymax>498</ymax>
		</bndbox>
	</object>
	<object>
		<name>eddy</name>
		<pose>Unspecified</pose>
		<truncated>0</truncated>
		<difficult>0</difficult>
		<bndbox>
			<xmin>310</xmin>
			<ymin>2</ymin>
			<xmax>336</xmax>
			<ymax>36</ymax>
		</bndbox>
	</object>
	<object>
		<name>eddy</name>
		<pose>Unspecified</pose>
		<truncated>0</truncated>
		<difficult>0</difficult>
		<bndbox>
			<xmin>4</xmin>
			<ymin>18</ymin>
			<xmax>68</xmax>
			<ymax>93</ymax>
		</bndbox>
	</object>
	<object>
		<name>eddy</name>
		<pose>Unspecified</pose>
		<truncated>0</truncated>
		<difficult>0</difficult>
		<bndbox>
			<xmin>446</xmin>
			<ymin>188</ymin>
			<xmax>499</xmax>
			<ymax>230</ymax>
		</bndbox>
	</object>
	<object>
		<name>eddy</name>
		<pose>Unspecified</pose>
		<truncated>0</truncated>
		<difficult>0</difficult>
		<bndbox>
			<xmin>243</xmin>
			<ymin>305</ymin>
			<xmax>307</xmax>
			<ymax>395</ymax>
		</bndbox>
	</object>
	<object>
		<name>eddy</name>
		<pose>Unspecified</pose>
		<truncated>0</truncated>
		<difficult>0</difficult>
		<bndbox>
			<xmin>347</xmin>
			<ymin>279</ymin>
			<xmax>415</xmax>
			<ymax>345</ymax>
		</bndbox>
	</object>
	<object>
		<name>eddy</name>
		<pose>Unspecified</pose>
		<truncated>0</truncated>
		<difficult>0</difficult>
		<bndbox>
			<xmin>433</xmin>
			<ymin>343</ymin>
			<xmax>465</xmax>
			<ymax>386</ymax>
		</bndbox>
	</object>
</annotation>
