<annotation>
	<folder>img</folder>
	<filename>001636.jpg</filename>
	<path>F:\VOCData\augment\291\img\001636.jpg</path>
	<source>
		<database>Unknown</database>
	</source>
	<size>
		<width>512</width>
		<height>512</height>
		<depth>3</depth>
	</size>
	<segmented>0</segmented>
	<object>
		<name>eddy</name>
		<pose>Unspecified</pose>
		<truncated>0</truncated>
		<difficult>0</difficult>
		<bndbox>
			<xmin>125</xmin>
			<ymin>34</ymin>
			<xmax>177</xmax>
			<ymax>84</ymax>
		</bndbox>
	</object>
	<object>
		<name>eddy</name>
		<pose>Unspecified</pose>
		<truncated>0</truncated>
		<difficult>0</difficult>
		<bndbox>
			<xmin>373</xmin>
			<ymin>119</ymin>
			<xmax>415</xmax>
			<ymax>159</ymax>
		</bndbox>
	</object>
	<object>
		<name>eddy</name>
		<pose>Unspecified</pose>
		<truncated>0</truncated>
		<difficult>0</difficult>
		<bndbox>
			<xmin>423</xmin>
			<ymin>186</ymin>
			<xmax>464</xmax>
			<ymax>230</ymax>
		</bndbox>
	</object>
	<object>
		<name>eddy</name>
		<pose>Unspecified</pose>
		<truncated>0</truncated>
		<difficult>0</difficult>
		<bndbox>
			<xmin>310</xmin>
			<ymin>162</ymin>
			<xmax>343</xmax>
			<ymax>194</ymax>
		</bndbox>
	</object>
	<object>
		<name>eddy</name>
		<pose>Unspecified</pose>
		<truncated>0</truncated>
		<difficult>0</difficult>
		<bndbox>
			<xmin>363</xmin>
			<ymin>269</ymin>
			<xmax>403</xmax>
			<ymax>325</ymax>
		</bndbox>
	</object>
	<object>
		<name>eddy</name>
		<pose>Unspecified</pose>
		<truncated>0</truncated>
		<difficult>0</difficult>
		<bndbox>
			<xmin>151</xmin>
			<ymin>100</ymin>
			<xmax>220</xmax>
			<ymax>145</ymax>
		</bndbox>
	</object>
	<object>
		<name>eddy</name>
		<pose>Unspecified</pose>
		<truncated>0</truncated>
		<difficult>0</difficult>
		<bndbox>
			<xmin>253</xmin>
			<ymin>150</ymin>
			<xmax>279</xmax>
			<ymax>174</ymax>
		</bndbox>
	</object>
	<object>
		<name>eddy</name>
		<pose>Unspecified</pose>
		<truncated>0</truncated>
		<difficult>0</difficult>
		<bndbox>
			<xmin>20</xmin>
			<ymin>84</ymin>
			<xmax>73</xmax>
			<ymax>148</ymax>
		</bndbox>
	</object>
	<object>
		<name>eddy</name>
		<pose>Unspecified</pose>
		<truncated>0</truncated>
		<difficult>0</difficult>
		<bndbox>
			<xmin>186</xmin>
			<ymin>204</ymin>
			<xmax>281</xmax>
			<ymax>253</ymax>
		</bndbox>
	</object>
	<object>
		<name>eddy</name>
		<pose>Unspecified</pose>
		<truncated>0</truncated>
		<difficult>0</difficult>
		<bndbox>
			<xmin>339</xmin>
			<ymin>381</ymin>
			<xmax>401</xmax>
			<ymax>437</ymax>
		</bndbox>
	</object>
	<object>
		<name>eddy</name>
		<pose>Unspecified</pose>
		<truncated>1</truncated>
		<difficult>0</difficult>
		<bndbox>
			<xmin>341</xmin>
			<ymin>488</ymin>
			<xmax>374</xmax>
			<ymax>512</ymax>
		</bndbox>
	</object>
	<object>
		<name>eddy</name>
		<pose>Unspecified</pose>
		<truncated>0</truncated>
		<difficult>0</difficult>
		<bndbox>
			<xmin>295</xmin>
			<ymin>306</ymin>
			<xmax>339</xmax>
			<ymax>358</ymax>
		</bndbox>
	</object>
	<object>
		<name>eddy</name>
		<pose>Unspecified</pose>
		<truncated>0</truncated>
		<difficult>0</difficult>
		<bndbox>
			<xmin>192</xmin>
			<ymin>262</ymin>
			<xmax>239</xmax>
			<ymax>304</ymax>
		</bndbox>
	</object>
	<object>
		<name>eddy</name>
		<pose>Unspecified</pose>
		<truncated>1</truncated>
		<difficult>0</difficult>
		<bndbox>
			<xmin>1</xmin>
			<ymin>168</ymin>
			<xmax>52</xmax>
			<ymax>208</ymax>
		</bndbox>
	</object>
	<object>
		<name>eddy</name>
		<pose>Unspecified</pose>
		<truncated>0</truncated>
		<difficult>0</difficult>
		<bndbox>
			<xmin>82</xmin>
			<ymin>269</ymin>
			<xmax>130</xmax>
			<ymax>346</ymax>
		</bndbox>
	</object>
	<object>
		<name>eddy</name>
		<pose>Unspecified</pose>
		<truncated>0</truncated>
		<difficult>0</difficult>
		<bndbox>
			<xmin>219</xmin>
			<ymin>344</ymin>
			<xmax>283</xmax>
			<ymax>391</ymax>
		</bndbox>
	</object>
	<object>
		<name>eddy</name>
		<pose>Unspecified</pose>
		<truncated>0</truncated>
		<difficult>0</difficult>
		<bndbox>
			<xmin>198</xmin>
			<ymin>427</ymin>
			<xmax>256</xmax>
			<ymax>473</ymax>
		</bndbox>
	</object>
	<object>
		<name>eddy</name>
		<pose>Unspecified</pose>
		<truncated>0</truncated>
		<difficult>0</difficult>
		<bndbox>
			<xmin>115</xmin>
			<ymin>397</ymin>
			<xmax>157</xmax>
			<ymax>436</ymax>
		</bndbox>
	</object>
	<object>
		<name>eddy</name>
		<pose>Unspecified</pose>
		<truncated>0</truncated>
		<difficult>0</difficult>
		<bndbox>
			<xmin>12</xmin>
			<ymin>259</ymin>
			<xmax>42</xmax>
			<ymax>314</ymax>
		</bndbox>
	</object>
	<object>
		<name>eddy</name>
		<pose>Unspecified</pose>
		<truncated>0</truncated>
		<difficult>0</difficult>
		<bndbox>
			<xmin>36</xmin>
			<ymin>343</ymin>
			<xmax>82</xmax>
			<ymax>392</ymax>
		</bndbox>
	</object>
	<object>
		<name>eddy</name>
		<pose>Unspecified</pose>
		<truncated>1</truncated>
		<difficult>0</difficult>
		<bndbox>
			<xmin>463</xmin>
			<ymin>479</ymin>
			<xmax>505</xmax>
			<ymax>512</ymax>
		</bndbox>
	</object>
	<object>
		<name>eddy</name>
		<pose>Unspecified</pose>
		<truncated>0</truncated>
		<difficult>0</difficult>
		<bndbox>
			<xmin>380</xmin>
			<ymin>436</ymin>
			<xmax>407</xmax>
			<ymax>466</ymax>
		</bndbox>
	</object>
	<object>
		<name>eddy</name>
		<pose>Unspecified</pose>
		<truncated>0</truncated>
		<difficult>0</difficult>
		<bndbox>
			<xmin>258</xmin>
			<ymin>278</ymin>
			<xmax>285</xmax>
			<ymax>312</ymax>
		</bndbox>
	</object>
</annotation>
