<?xml version="1.0" ?>
<annotation>
    <folder>AIA AUTO</folder>
    <filename>000317_flip_type-1.jpg</filename>
    <source>
        <database>The AUTO Database</database>
        <annotation>AUTO by zxl</annotation>
        <image>flickr</image>
    </source>
    <size>
        <width>300</width>
        <height>300</height>
        <depth>3</depth>
    </size>
    <object>
        <name>eddy</name>
        <pose>front</pose>
        <truncated>0</truncated>
        <difficult>0</difficult>
        <bndbox>
            <xmin>229</xmin>
            <ymin>51</ymin>
            <xmax>271</xmax>
            <ymax>88</ymax>
        </bndbox>
    </object>
    <object>
        <name>eddy</name>
        <pose>front</pose>
        <truncated>0</truncated>
        <difficult>0</difficult>
        <bndbox>
            <xmin>103</xmin>
            <ymin>108</ymin>
            <xmax>140</xmax>
            <ymax>167</ymax>
        </bndbox>
    </object>
    <object>
        <name>eddy</name>
        <pose>front</pose>
        <truncated>0</truncated>
        <difficult>0</difficult>
        <bndbox>
            <xmin>138</xmin>
            <ymin>159</ymin>
            <xmax>180</xmax>
            <ymax>210</ymax>
        </bndbox>
    </object>
    <object>
        <name>eddy</name>
        <pose>front</pose>
        <truncated>0</truncated>
        <difficult>0</difficult>
        <bndbox>
            <xmin>78</xmin>
            <ymin>192</ymin>
            <xmax>125</xmax>
            <ymax>237</ymax>
        </bndbox>
    </object>
    <object>
        <name>eddy</name>
        <pose>front</pose>
        <truncated>0</truncated>
        <difficult>0</difficult>
        <bndbox>
            <xmin>160</xmin>
            <ymin>252</ymin>
            <xmax>187</xmax>
            <ymax>278</ymax>
        </bndbox>
    </object>
    <object>
        <name>eddy</name>
        <pose>front</pose>
        <truncated>0</truncated>
        <difficult>0</difficult>
        <bndbox>
            <xmin>264</xmin>
            <ymin>194</ymin>
            <xmax>299</xmax>
            <ymax>225</ymax>
        </bndbox>
    </object>
    <object>
        <name>eddy</name>
        <pose>front</pose>
        <truncated>0</truncated>
        <difficult>0</difficult>
        <bndbox>
            <xmin>46</xmin>
            <ymin>6</ymin>
            <xmax>104</xmax>
            <ymax>44</ymax>
        </bndbox>
    </object>
    <object>
        <name>eddy</name>
        <pose>front</pose>
        <truncated>0</truncated>
        <difficult>0</difficult>
        <bndbox>
            <xmin>173</xmin>
            <ymin>3</ymin>
            <xmax>198</xmax>
            <ymax>24</ymax>
        </bndbox>
    </object>
    <object>
        <name>eddy</name>
        <pose>front</pose>
        <truncated>0</truncated>
        <difficult>0</difficult>
        <bndbox>
            <xmin>228</xmin>
            <ymin>101</ymin>
            <xmax>245</xmax>
            <ymax>116</ymax>
        </bndbox>
    </object>
</annotation>
