<annotation>
	<folder>512crop_jpg</folder>
	<filename>002512_rsize1024x600_crop512_0_wh512x512.jpg</filename>
	<path>F:\VOCData\augment\2500\512crop_jpg\002512_rsize1024x600_crop512_0_wh512x512.jpg</path>
	<source>
		<database>Unknown</database>
	</source>
	<size>
		<width>512</width>
		<height>512</height>
		<depth>3</depth>
	</size>
	<segmented>0</segmented>
	<object>
		<name>eddy</name>
		<pose>Unspecified</pose>
		<truncated>0</truncated>
		<difficult>0</difficult>
		<bndbox>
			<xmin>356</xmin>
			<ymin>80</ymin>
			<xmax>452</xmax>
			<ymax>136</ymax>
		</bndbox>
	</object>
	<object>
		<name>eddy</name>
		<pose>Unspecified</pose>
		<truncated>0</truncated>
		<difficult>0</difficult>
		<bndbox>
			<xmin>347</xmin>
			<ymin>262</ymin>
			<xmax>427</xmax>
			<ymax>298</ymax>
		</bndbox>
	</object>
	<object>
		<name>eddy</name>
		<pose>Unspecified</pose>
		<truncated>0</truncated>
		<difficult>0</difficult>
		<bndbox>
			<xmin>62</xmin>
			<ymin>316</ymin>
			<xmax>237</xmax>
			<ymax>431</ymax>
		</bndbox>
	</object>
	<object>
		<name>eddy</name>
		<pose>Unspecified</pose>
		<truncated>0</truncated>
		<difficult>0</difficult>
		<bndbox>
			<xmin>304</xmin>
			<ymin>153</ymin>
			<xmax>440</xmax>
			<ymax>250</ymax>
		</bndbox>
	</object>
</annotation>
